odoo8_addon_l10n_it_withholding_tax_payment-8.0.2.1.0-py3.6-nspkg.pth
odoo_addons/l10n_it_withholding_tax_payment/README.rst
odoo_addons/l10n_it_withholding_tax_payment/__init__.py
odoo_addons/l10n_it_withholding_tax_payment/__openerp__.py
odoo_addons/l10n_it_withholding_tax_payment/workflow.xml
odoo_addons/l10n_it_withholding_tax_payment/data/sequence.xml
odoo_addons/l10n_it_withholding_tax_payment/i18n/it.po
odoo_addons/l10n_it_withholding_tax_payment/i18n/l10n_it_withholding_tax_payment.pot
odoo_addons/l10n_it_withholding_tax_payment/i18n/sl.po
odoo_addons/l10n_it_withholding_tax_payment/models/__init__.py
odoo_addons/l10n_it_withholding_tax_payment/models/withholding_tax.py
odoo_addons/l10n_it_withholding_tax_payment/security/ir.model.access.csv
odoo_addons/l10n_it_withholding_tax_payment/static/description/icon.png
odoo_addons/l10n_it_withholding_tax_payment/views/withholding_tax.xml
odoo_addons/l10n_it_withholding_tax_payment/wizard/__init__.py
odoo_addons/l10n_it_withholding_tax_payment/wizard/create_move_payment.py
odoo_addons/l10n_it_withholding_tax_payment/wizard/create_move_payment_view.xml
odoo8_addon_l10n_it_withholding_tax_payment-8.0.2.1.0.dist-info/METADATA
odoo8_addon_l10n_it_withholding_tax_payment-8.0.2.1.0.dist-info/WHEEL
odoo8_addon_l10n_it_withholding_tax_payment-8.0.2.1.0.dist-info/namespace_packages.txt
odoo8_addon_l10n_it_withholding_tax_payment-8.0.2.1.0.dist-info/top_level.txt
odoo8_addon_l10n_it_withholding_tax_payment-8.0.2.1.0.dist-info/RECORD
