Metadata-Version: 2.1
Name: odoo8-addon-l10n-it-withholding-tax-payment
Version: 8.0.2.1.0
Summary: Italian Withholding Tax Payment
Home-page: http://www.openforce.it
Author: Openforce di Alessandro Camilli, Odoo Community Association (OCA)
Author-email: support@odoo-community.org
License: AGPL-3
Platform: UNKNOWN
Classifier: Programming Language :: Python
Classifier: Framework :: Odoo
Classifier: License :: OSI Approved :: GNU Affero General Public License v3
Requires-Python: ~=2.7
Requires-Dist: odoo8-addon-l10n-it-withholding-tax
Requires-Dist: odoo (<9.0a,>=8.0a)
